dissect/hypervisor/__init__.py
dissect/hypervisor/exceptions.py
dissect/hypervisor/descriptor/__init__.py
dissect/hypervisor/descriptor/c_hyperv.py
dissect/hypervisor/descriptor/hyperv.py
dissect/hypervisor/descriptor/ovf.py
dissect/hypervisor/descriptor/pvs.py
dissect/hypervisor/descriptor/vbox.py
dissect/hypervisor/descriptor/vmx.py
dissect/hypervisor/disk/__init__.py
dissect/hypervisor/disk/c_hdd.py
dissect/hypervisor/disk/c_qcow2.py
dissect/hypervisor/disk/c_qcow2.pyi
dissect/hypervisor/disk/c_vdi.py
dissect/hypervisor/disk/c_vhd.py
dissect/hypervisor/disk/c_vhdx.py
dissect/hypervisor/disk/c_vmdk.py
dissect/hypervisor/disk/hdd.py
dissect/hypervisor/disk/qcow2.py
dissect/hypervisor/disk/vdi.py
dissect/hypervisor/disk/vhd.py
dissect/hypervisor/disk/vhdx.py
dissect/hypervisor/disk/vmdk.py
dissect/hypervisor/tools/__init__.py
dissect/hypervisor/tools/envelope.py
dissect/hypervisor/tools/vmtar.py
dissect/hypervisor/util/__init__.py
dissect/hypervisor/util/envelope.py
dissect/hypervisor/util/vmtar.py
dissect_hypervisor-3.19.dist-info/licenses/COPYRIGHT
dissect_hypervisor-3.19.dist-info/licenses/LICENSE
dissect_hypervisor-3.19.dist-info/METADATA
dissect_hypervisor-3.19.dist-info/WHEEL
dissect_hypervisor-3.19.dist-info/entry_points.txt
dissect_hypervisor-3.19.dist-info/top_level.txt
dissect_hypervisor-3.19.dist-info/RECORD
